lit_python_sdk/__init__.py
lit_python_sdk/client.py
lit_python_sdk/lit_account.py
lit_python_sdk/lit_pkp_backend.py
lit_python_sdk/lit_wallet_address.py
lit_python_sdk/server.py
lit_python_sdk/signing.py
lit_python_sdk/bundled_server.js
lit_python_sdk-1.2.3.dist-info/METADATA
lit_python_sdk-1.2.3.dist-info/WHEEL
lit_python_sdk-1.2.3.dist-info/RECORD
