Metadata-Version: 2.4
Name: lit-python-sdk
Version: 1.2.3
Summary: A Python SDK for executing JavaScript code via Node.js
Project-URL: Homepage, https://github.com/lit-protocol/lit-python-sdk
Project-URL: Bug Tracker, https://github.com/lit-protocol/lit-python-sdk/issues
Author-email: Chris Cassano <chris@litprotocol.com>
Requires-Python: >=3.7
Requires-Dist: eth-account>=0.13.3
Requires-Dist: nodejs-bin>=18.4.0a4
Requires-Dist: python-dotenv>=1.0.1
Requires-Dist: requests>=2.25.0
